dlco-exp/registerandmemory/register/register.v
/* verilator lint_off LATCH */
/* verilator lint_off MULTIDRIVEN */
/* verilator lint_off SYNCASYNCNET */
module register(load, clk, pre, clr, in, q);
	input load, clk, pre, clr, in;
	output reg q;

	always@(pre, clr) begin
	
	if(clr == 1)
		q <= 0;
	else if(pre == 1)
		q <= 1;	
		
	end
	
	always@(posedge clk)

		if(pre!=1 && clr!=1)		
			if(load == 1)
				q <= in;
	
endmodule
/* verilator lint_on LATCH */
/* verilator lint_on MULTIDRIVEN */
/* verilator lint_off SYNCASYNCNET */

dlco-exp/registerandmemory/register/dump.vcd
$version Generated by VerilatedVcd $end
$timescale 1s $end

 $scope module TOP $end
  $var wire  1 $ clk $end
  $var wire  1 & clr $end
  $var wire  1 ' in $end
  $var wire  1 # load $end
  $var wire  1 % pre $end
  $var wire  1 ( q $end
  $scope module register $end
   $var wire  1 $ clk $end
   $var wire  1 & clr $end
   $var wire  1 ' in $end
   $var wire  1 # load $end
   $var wire  1 % pre $end
   $var wire  1 ( q $end
  $upscope $end
 $upscope $end
$enddefinitions $end


#1
1#
0$
1%
0&
1'
1(
#2
1$
#3
0$
0%
1&
0(
#4
1$
#5
0#
0$
0&
#6
1$
#7
0$
0'
#8
1$
#9
1#
0$
1'
#10
1$
1(
#11
0$
0'
#12
1$
0(
#13
0$
1'
#14
1$
1(
#15
0$
1&
0(
