dlco-exp/chooser/jgxzq/jgxzq.v
/* verilator lint_off DECLFILENAME */
module my_anddoor(a, b, c);
	input a,b;
	output c;
	
	assign c = a&b;
endmodule

module my_ordoor(a, b, c);
	input a, b;
	output c;
	
	assign c = a|b;
endmodule

module my_notdoor(a, c);
	input a;
	output c;
	
	assign c = ~a;
endmodule
/* verilator lint_on DECLFILENAME */

module jgxzq(a, b, c, y);
	input a, b, c;
	output y;
	
	wire l, r, b_n;
	my_notdoor i1(.a(b), .c(b_n));
	my_anddoor i2(.a(a), .b(b), .c(l));
	my_anddoor i3(.a(b_n), .b(c), .c(r));
	my_ordoor  i4(.a(l), .b(r), .c(y));

endmodule

dlco-exp/chooser/jgxzq/obj_dir/dump.vcd
$version Generated by VerilatedVcd $end
$timescale 1s $end

 $scope module TOP $end
  $var wire  1 # a $end
  $var wire  1 $ b $end
  $var wire  1 % c $end
  $var wire  1 & y $end
  $scope module jgxzq $end
   $var wire  1 # a $end
   $var wire  1 $ b $end
   $var wire  1 ) b_n $end
   $var wire  1 % c $end
   $var wire  1 ' l $end
   $var wire  1 ( r $end
   $var wire  1 & y $end
   $scope module i1 $end
    $var wire  1 $ a $end
    $var wire  1 ) c $end
   $upscope $end
   $scope module i2 $end
    $var wire  1 # a $end
    $var wire  1 $ b $end
    $var wire  1 ' c $end
   $upscope $end
   $scope module i3 $end
    $var wire  1 ) a $end
    $var wire  1 % b $end
    $var wire  1 ( c $end
   $upscope $end
   $scope module i4 $end
    $var wire  1 ' a $end
    $var wire  1 ( b $end
    $var wire  1 & c $end
   $upscope $end
  $upscope $end
 $upscope $end
$enddefinitions $end


#1
0#
0$
0%
0&
0'
0(
1)
#2
1%
1&
1(
#3
1#
0%
0&
0(
#4
1%
1&
1(
#5
0#
1$
0%
0&
0(
0)
#6
1%
#7
1#
0%
1&
1'
#8
1%
