dlco-exp/adder/ALU/ALU.v
module ALU(x, y, judge, result, overflow);

	input[7:0]x, y;
	input [2:0]judge;
	output reg [7:0]result;
	output reg overflow;
	/* verilator lint_off LATCH */
	always @(x or y or judge or result or overflow)
	begin
	/* verilator lint_off WIDTH */
		if(judge==3'b000)
		begin
			result = 8'b00000000;
			overflow = 1'b0;
			
			result = x+y;
			
			overflow = (x[7]==y[7]) && (result[7]!=x[7]);
		
		end
		if(judge==3'b001)
		begin
			result = 8'b00000000;
			overflow = 1'b0;
			result = (x-y);
			overflow = (x[7]!=y[7]) && (result[7]!=x[7]);
			
		end
		else
		begin	
			overflow = 0;
			case (judge)
				
				3'b010:
					result = ~x;
				3'b011:
					result = x&y;
				3'b100:
					result = x|y;
				3'b101:
					result = x^y;
				3'b110:
					result = ((x>y) && (x[7]==y[7])) || (((x-y)<127) && (x[7]!=y[7]));
				3'b111:
					result = (x==y);
				default:
					result = 0;
			endcase
		
		end
	/* verilator lint_on WIDTH */
	end
	/* verilator lint_on LATCH */
endmodule

dlco-exp/adder/ALU/dump.vcd
$version Generated by VerilatedVcd $end
$date Fri Jul 14 20:09:50 2023 $end
$timescale 1s $end

 $scope module TOP $end
  $var wire  3 % judge [2:0] $end
  $var wire  1 ' overflow $end
  $var wire  8 & result [7:0] $end
  $var wire  8 # x [7:0] $end
  $var wire  8 $ y [7:0] $end
  $scope module ALU $end
   $var wire  3 % judge [2:0] $end
   $var wire  1 ' overflow $end
   $var wire  8 & result [7:0] $end
   $var wire  8 # x [7:0] $end
   $var wire  8 $ y [7:0] $end
  $upscope $end
 $upscope $end
$enddefinitions $end


#1
b00000010 #
b00000001 $
b000 %
b00000000 &
0'
#2
b00001000 $
#3
b01111111 $
#4
b00001000 #
b00000001 $
b001 %
b00000111 &
#5
b00010000 $
b11111000 &
#6
b00000000 #
b00000000 $
b010 %
b11111111 &
#7
b01010110 #
b00000100 $
b011 %
b00000100 &
#8
b10101010 #
b01010101 $
b100 %
b11111111 &
#9
b00000010 #
b00000001 $
b101 %
b00000011 &
#10
b11111111 #
b00000010 $
b110 %
b00000000 &
#11
b11111110 #
b11111101 $
b00000001 &
#12
b11111110 $
b00000000 &
#13
b00000001 #
b00000011 $
b111 %
#14
b00000001 $
b00000001 &
