dlco-exp/adder/ALU/ALU.v
module ALU(x, y, judge, result, overflow);

	input[7:0]x, y;
	input [2:0]judge;
	output reg [7:0]result;
	output reg overflow;
	always @(x or y or judge or result or overflow)
	begin
	
		if(judge==3'b000)
		begin
			result = 8'b00000000;
			overflow = 1'b0;
			
			result = x+y;
			/* verilator lint_off UNSIGNED */
			/* verilator lint_off SELRANGE */
			overflow = (x[7]==y[7]) && (result[7]!=x[7]);
			/* verilator lint_on SELRANGE */
		end
		if(judge==3'b001)
		begin
			result = 8'b00000000;
			overflow = 1'b0;
			
			/* verilator lint_off WIDTHEXPAND */
			/* verilator lint_off WIDTHTRUNC */
			result = (x-y);
			/* verilator lint_on WIDTHEXPAND */
			/* verilator lint_on WIDTHTRUNC */
			/* verilator lint_off SELRANGE */
			overflow = (x[7]==y[7]) && (result[7]!=x[7]);
			/* verilator lint_on UNSIGNED */
			/* verilator lint_on SELRANGE */
		end
		else
		begin	
			/* verilator lint_off CASEINCOMPLETE */
			case (judge)
			/* verilator lint_off WIDTHTRUNC */
			/* verilator lint_off WIDTHEXPAND */	
				3'b010:
					result = ~x;
				3'b011:
					result = x&y;
				3'b100:
					result = x|y;
				3'b101:
					result = x^y;
				3'b110:
					result = x>y;
				3'b111:
					result = (x==y);
			/* verilator lint_on WIDTHTRUNC */
			/* verilator lint_on WIDTHEXPAND */
			endcase
			/* verilator lint_on CASEINCOMPLETE */
		end
	end
endmodule

dlco-exp/adder/ALU/dump.vcd
$version Generated by VerilatedVcd $end
$timescale 1s $end

 $scope module TOP $end
  $var wire  3 % judge [2:0] $end
  $var wire  1 ' overflow $end
  $var wire  8 & result [7:0] $end
  $var wire  8 # x [7:0] $end
  $var wire  8 $ y [7:0] $end
  $scope module ALU $end
   $var wire  3 % judge [2:0] $end
   $var wire  1 ' overflow $end
   $var wire  8 & result [7:0] $end
   $var wire  8 # x [7:0] $end
   $var wire  8 $ y [7:0] $end
  $upscope $end
 $upscope $end
$enddefinitions $end


#1
b00000010 #
b00000001 $
b000 %
b00000011 &
0'
#2
b00001000 $
b00001010 &
#3
b01111111 $
b10000001 &
1'
#4
b00001000 #
b00000001 $
b001 %
b00000111 &
0'
#5
b00010000 $
b11111000 &
1'
#6
b00000000 #
b00000000 $
b010 %
b11111111 &
#7
b01010110 #
b00000100 $
b011 %
b00000100 &
#8
b10101010 #
b01010101 $
b100 %
b11111111 &
#9
b00000010 #
b00000001 $
b101 %
b00000011 &
#10
b11111110 #
b110 %
b00000001 &
#11
b00000001 #
b00000011 $
b111 %
b00000000 &
#12
b00000001 $
b00000001 &
