dlco-exp/adder/fulladder/fulladder.v
/* verilator lint_off DECLFILENAME */
module my_anddoor(a, b, c);
	input a,b;
	output c;
	
	assign c = a&b;
endmodule

module my_ordoor(a, b, c);
	input a, b;
	output c;
	
	assign c = a|b;
endmodule

module my_xordoor(a, b, c);
	input a, b;
	output c;
	
	assign c = a^b;
endmodule
/* verilator lint_on DECLFILENAME */

module fulladder(j, a, b, s, l);
	input j, a, b;
	output s, l;
	
	wire k, w, h;
	
	my_xordoor i1(.a(a), .b(b), .c(k));
	my_anddoor i2(.a(a), .b(b), .c(w));
	
	my_xordoor i3(.a(j), .b(k), .c(l));
	my_anddoor i4(.a(j), .b(k), .c(h));
	
	my_ordoor i5(.a(w), .b(h), .c(s));
	
endmodule

dlco-exp/adder/fulladder/dump.vcd
$version Generated by VerilatedVcd $end
$timescale 1s $end

 $scope module TOP $end
  $var wire  1 $ a $end
  $var wire  1 % b $end
  $var wire  1 # j $end
  $var wire  1 ' l $end
  $var wire  1 & s $end
  $scope module fulladder $end
   $var wire  1 $ a $end
   $var wire  1 % b $end
   $var wire  1 * h $end
   $var wire  1 # j $end
   $var wire  1 ( k $end
   $var wire  1 ' l $end
   $var wire  1 & s $end
   $var wire  1 ) w $end
   $scope module i1 $end
    $var wire  1 $ a $end
    $var wire  1 % b $end
    $var wire  1 ( c $end
   $upscope $end
   $scope module i2 $end
    $var wire  1 $ a $end
    $var wire  1 % b $end
    $var wire  1 ) c $end
   $upscope $end
   $scope module i3 $end
    $var wire  1 # a $end
    $var wire  1 ( b $end
    $var wire  1 ' c $end
   $upscope $end
   $scope module i4 $end
    $var wire  1 # a $end
    $var wire  1 ( b $end
    $var wire  1 * c $end
   $upscope $end
   $scope module i5 $end
    $var wire  1 ) a $end
    $var wire  1 * b $end
    $var wire  1 & c $end
   $upscope $end
  $upscope $end
 $upscope $end
$enddefinitions $end


#1
0#
0$
0%
0&
0'
0(
0)
0*
#2
1%
1'
1(
#3
1$
0%
#4
1%
1&
0'
0(
1)
#5
1#
0$
0%
0&
1'
0)
#6
1%
1&
0'
1(
1*
#7
1$
0%
#8
1%
1'
0(
1)
0*
